odoo/addons/l10n_de_skr03_mis_reports/README.rst
odoo/addons/l10n_de_skr03_mis_reports/__init__.py
odoo/addons/l10n_de_skr03_mis_reports/__manifest__.py
odoo/addons/l10n_de_skr03_mis_reports/data/mis_report_bs.xml
odoo/addons/l10n_de_skr03_mis_reports/data/mis_report_pl.xml
odoo/addons/l10n_de_skr03_mis_reports/data/mis_report_styles.xml
odoo/addons/l10n_de_skr03_mis_reports/i18n/de.po
odoo/addons/l10n_de_skr03_mis_reports/i18n/l10n_de_skr03_mis_reports.pot
odoo/addons/l10n_de_skr03_mis_reports/static/description/icon.png
odoo11_addon_l10n_de_skr03_mis_reports-11.0.1.1.0.99.dev2.dist-info/METADATA
odoo11_addon_l10n_de_skr03_mis_reports-11.0.1.1.0.99.dev2.dist-info/RECORD
odoo11_addon_l10n_de_skr03_mis_reports-11.0.1.1.0.99.dev2.dist-info/WHEEL
odoo11_addon_l10n_de_skr03_mis_reports-11.0.1.1.0.99.dev2.dist-info/top_level.txt
